pdf_wrangler/__init__.py
pdf_wrangler/document.py
pdf_wrangler/page.py
pdf_wrangler-0.0.31.dist-info/LICENSE
pdf_wrangler-0.0.31.dist-info/METADATA
pdf_wrangler-0.0.31.dist-info/WHEEL
pdf_wrangler-0.0.31.dist-info/top_level.txt
pdf_wrangler-0.0.31.dist-info/RECORD
