Metadata-Version: 2.1
Name: pdf-wrangler
Version: 0.0.31
Summary: PDFMiner Wrapper for extractions
Home-page: https://github.com/happilyeverafter95/pdf-wrangler
Author: happilyeverafter95
Author-email: author@example.com
License: UNKNOWN
Project-URL: Bug Tracker, https://github.com/happilyeverafter95/pdf-wrangler/issues
Keywords: pdf parser,text mining
Platform: UNKNOWN
Classifier: Programming Language :: Python :: 3
Classifier: License :: OSI Approved :: MIT License
Classifier: Operating System :: OS Independent
Requires-Python: >=3.6
Requires-Dist: chardet (==3.0.4)
Requires-Dist: pdfminer.six (==20181108)
